{
  "wp_code": "A22-1",
  "name": "项目负责经理复核(适用于财报审计)",
  "version": "2025-R1",
  "cycle": "A",
  "cycle_name": "完成阶段",
  "source_files": [
    {
      "file": "项目负责经理复核(适用于财报审计).xlsx",
      "sheets": [
        "底稿目录",
        "A22-1 项目负责经理复核(适用于财报审计)",
        " A22-1-1 复核记录"
      ]
    }
  ],
  "sheet_rules": [
    {
      "exact_name": "A22-1 项目负责经理复核(适用于财报审计)",
      "type": "check",
      "code": "A22-1"
    },
    {
      "exact_name": " A22-1-1 复核记录",
      "type": "check",
      "code": "A22-1"
    }
  ],
  "cross_references": [],
  "audit_checks": [
    {
      "code": "A22-1-CHK-01",
      "type": "completeness",
      "severity": "warning",
      "description": "底稿已填写完整（关键Sheet有数据）"
    },
    {
      "code": "A22-1-CHK-02",
      "type": "check",
      "severity": "blocking",
      "description": "复核意见已签署"
    },
    {
      "id": "A22-1-CHK-03",
      "type": "check",
      "severity": "info",
      "description": "编制日期在审计期间内"
    }
  ]
}