{
  "wp_code": "H6",
  "name": "固定资产清理",
  "version": "2025-R1",
  "account_codes": [
    "1606"
  ],
  "source_files": [
    {
      "file": "固定资产清理.xlsx",
      "sheets": [
        "底稿目录",
        "固定资产清理实质性程序表H6A",
        "审定表H6-1",
        "附注披露信息（上市公司）",
        "附注披露信息（国有企业）",
        "明细表H6-2",
        "调整分录汇总H6-3",
        "检查表H6-4"
      ]
    }
  ],
  "sheet_rules": [
    {
      "exact_name": "固定资产清理实质性程序表H6A",
      "type": "procedure",
      "code": "H6"
    },
    {
      "exact_name": "审定表H6-1",
      "type": "summary",
      "header_rows": [
        5,
        6
      ],
      "data_start_row": 7,
      "code": "H6-1"
    },
    {
      "exact_name": "附注披露信息（上市公司）",
      "type": "note_disclosure",
      "code": "附注披露信息（上市公司）"
    },
    {
      "exact_name": "附注披露信息（国有企业）",
      "type": "note_disclosure",
      "code": "附注披露信息（国有企业）"
    },
    {
      "exact_name": "明细表H6-2",
      "type": "detail",
      "code": "H6-2"
    },
    {
      "exact_name": "调整分录汇总H6-3",
      "type": "adjustment",
      "code": "H6-3"
    },
    {
      "exact_name": "检查表H6-4",
      "type": "check",
      "code": "H6-4"
    }
  ],
  "cross_references": [
    {
      "from": "H6-1.total",
      "to": "tb://1606#审定数",
      "description": "审定表合计 = 试算表固定资产清理审定数"
    },
    {
      "from": "H6-2.合计",
      "to": "H6-1.total",
      "description": "明细表合计 = 审定表合计"
    }
  ],
  "audit_checks": [
    {
      "code": "H6-CHK-01",
      "type": "balance",
      "severity": "blocking",
      "description": "审定表合计 = 试算表固定资产清理审定数"
    },
    {
      "code": "H6-CHK-02",
      "type": "cross_ref",
      "severity": "warning",
      "description": "明细表合计 = 审定表合计"
    },
    {
      "code": "H6-CHK-03",
      "type": "movement",
      "severity": "info",
      "description": "期初 + 变动 = 期末"
    },
    {
      "code": "H6-CHK-04",
      "type": "completeness",
      "severity": "warning",
      "description": "明细表数据完整"
    }
  ]
}