{
  "wp_code": "K8",
  "name": "销售费用",
  "version": "2025-R2",
  "account_codes": [
    "6601"
  ],
  "source_files": [
    {
      "file": "销售费用.xlsx",
      "sheets": [
        "底稿目录",
        "实质性程序表K8A",
        "审定表K8-1",
        "附注披露信息（上市公司）",
        "附注披露信息（国企）",
        "明细表K8-2",
        "调整分录汇总K8-3",
        "实质性分析K8-4",
        "合同检查表K8-5",
        "截止性测试(从记账凭证至原始凭证）K8-6",
        "截止性测试（从原始凭证至记账凭证）K8-7",
        "销售费用检查表K8-8"
      ]
    }
  ],
  "sheet_rules": [
    {
      "exact_name": "实质性程序表K8A",
      "code": "K8A",
      "type": "procedure"
    },
    {
      "exact_name": "审定表K8-1",
      "code": "K8-1",
      "type": "summary",
      "header_rows": [
        5,
        6
      ],
      "data_start_row": 7,
      "layout": {
        "label_col": 1,
        "columns": {
          "current_unadjusted": {
            "col": 2,
            "label": "本期未审数"
          },
          "current_adjustment": {
            "col": 3,
            "label": "本期账项调整"
          },
          "current_reclass": {
            "col": 4,
            "label": "本期重分类调整"
          },
          "current_audited": {
            "col": 5,
            "label": "本期审定数"
          },
          "prior_unadjusted": {
            "col": 6,
            "label": "上期未审数"
          },
          "prior_audited": {
            "col": 7,
            "label": "上期审定数"
          },
          "change_amount": {
            "col": 8,
            "label": "变动额"
          },
          "change_rate": {
            "col": 9,
            "label": "变动率"
          }
        }
      },
      "key_rows": {
        "total": {
          "row": 17,
          "label": "合计",
          "is_total": true,
          "report_row": "IS-004"
        },
        "tb_balance": {
          "row": 19,
          "label": "试算平衡表数"
        },
        "diff": {
          "row": 20,
          "label": "差异数"
        }
      },
      "detail_discovery": {
        "mode": "auto",
        "start_row": 7,
        "end_rule": "before_first_total",
        "skip_empty": true,
        "description": "自动识别第7行到合计行之间的所有非空明细行",
        "example_labels": [
          "职工薪酬",
          "折旧费",
          "摊销费",
          "差旅费",
          "业务招待费"
        ]
      }
    },
    {
      "exact_name": "附注披露信息（上市公司）",
      "code": "K8-note-listed",
      "type": "note_disclosure"
    },
    {
      "exact_name": "附注披露信息（国企）",
      "code": "K8-note-soe",
      "type": "note_disclosure"
    },
    {
      "exact_name": "明细表K8-2",
      "code": "K8-2",
      "type": "detail"
    },
    {
      "exact_name": "调整分录汇总K8-3",
      "code": "K8-3",
      "type": "adjustment"
    },
    {
      "exact_name": "实质性分析K8-4",
      "type": "analysis",
      "code": "K8-4"
    },
    {
      "exact_name": "合同检查表K8-5",
      "type": "check",
      "code": "K8-5"
    },
    {
      "exact_name": "截止性测试(从记账凭证至原始凭证）K8-6",
      "type": "calculation",
      "code": "K8-6"
    },
    {
      "exact_name": "截止性测试（从原始凭证至记账凭证）K8-7",
      "type": "calculation",
      "code": "K8-7"
    },
    {
      "exact_name": "销售费用检查表K8-8",
      "type": "check",
      "code": "K8-8"
    }
  ],
  "cross_references": [
    {
      "from": "K8-1.R17.C5",
      "to": "tb://6601#审定数",
      "description": "审定表合计 = 试算表销售费用审定数"
    },
    {
      "from": "K8-1.R17.C5",
      "to": "REPORT('IS-004','本期')",
      "description": "审定表合计 = 利润表销售费用"
    },
    {
      "from": "K8-2.合计",
      "to": "K8-1.R17.C5",
      "description": "明细表合计 = 审定表合计"
    },
    {
      "from": "K8-1.R7.C5",
      "to": "J1-1.销售费用分配",
      "description": "职工薪酬 → 应付职工薪酬分配表"
    }
  ],
  "audit_checks": [
    {
      "code": "K8-CHK-01",
      "type": "balance",
      "severity": "blocking",
      "description": "审定表合计 = 试算表销售费用审定数"
    },
    {
      "code": "K8-CHK-02",
      "type": "cross_ref",
      "severity": "warning",
      "description": "明细表合计 = 审定表合计"
    },
    {
      "code": "K8-CHK-03",
      "type": "movement",
      "severity": "info",
      "description": "期初 + 变动 = 期末"
    },
    {
      "code": "K8-CHK-04",
      "type": "completeness",
      "severity": "warning",
      "description": "明细表数据完整"
    },
    {
      "code": "K8-CHK-05",
      "type": "cutoff",
      "severity": "warning",
      "description": "截止测试无跨期事项"
    },
    {
      "code": "K8-CHK-06",
      "type": "analysis",
      "severity": "info",
      "description": "月度/类别分析无异常波动"
    },
    {
      "code": "K8-CHK-07",
      "type": "check",
      "severity": "info",
      "description": "大额合同已检查"
    }
  ]
}