{
  "wp_code": "S35-4",
  "name": "商誉减值",
  "version": "2025-R1",
  "cycle": "S",
  "cycle_name": "特定项目",
  "source_files": [
    {
      "file": "商誉减值.xlsx",
      "sheets": [
        "S35-4程序表",
        "GT_Custom"
      ]
    }
  ],
  "sheet_rules": [
    {
      "exact_name": "S35-4程序表",
      "type": "procedure",
      "code": "S35-4"
    },
    {
      "exact_name": "GT_Custom",
      "type": "check",
      "code": "GT_Custom"
    }
  ],
  "cross_references": [],
  "audit_checks": [
    {
      "code": "S35-4-CHK-01",
      "type": "completeness",
      "severity": "warning",
      "description": "底稿已填写完整（关键Sheet有数据）"
    }
  ]
}